CMakeLists.txt
LICENSE
MANIFEST.in
README.md
pyproject.toml
setup.py
pysiclib/__init__.py
pysiclib/__init__.pyi
pysiclib.egg-info/PKG-INFO
pysiclib.egg-info/SOURCES.txt
pysiclib.egg-info/dependency_links.txt
pysiclib.egg-info/not-zip-safe
pysiclib.egg-info/requires.txt
pysiclib.egg-info/top_level.txt
pysiclib/_pysiclib/__init__.pyi
pysiclib/_pysiclib/adaptive.pyi
pysiclib/_pysiclib/linalg.pyi
pysiclib/_pysiclib/numerical.pyi
pysiclib/_pysiclib/stats.pyi
pysiclib/api/__init__.py
pysiclib/api/__init__.pyi
pysiclib/api/adaptive.py
pysiclib/api/adaptive.pyi
pysiclib/api/linalg.py
pysiclib/api/linalg.pyi
pysiclib/api/numerical.py
pysiclib/api/numerical.pyi
pysiclib/api/stats.py
pysiclib/api/stats.pyi